validacoes_usuarios/__init__.py
validacoes_usuarios/config.py
validacoes_usuarios/validacoes.py
validacoes_usuarios-1.0.1.dist-info/LICENSE
validacoes_usuarios-1.0.1.dist-info/METADATA
validacoes_usuarios-1.0.1.dist-info/WHEEL
validacoes_usuarios-1.0.1.dist-info/top_level.txt
validacoes_usuarios-1.0.1.dist-info/RECORD
