Metadata-Version: 2.1
Name: validacoes_usuarios
Version: 1.0.1
Summary: Biblioteca para validação de senha e e-mail para segurança de dados dos usuários.
Home-page: https://github.com/AlaiSeide/validacoes_usuarios.git
Author: Alai Seide
Author-email: tenw313@gmail.com
Classifier: Development Status :: 5 - Production/Stable
Classifier: Intended Audience :: Developers
Classifier: License :: OSI Approved :: MIT License
Classifier: Programming Language :: Python :: 3
Classifier: Programming Language :: Python :: 3.8
Classifier: Programming Language :: Python :: 3.9
Classifier: Programming Language :: Python :: 3.10
Requires-Python: >=3.8
License-File: LICENSE
Requires-Dist: wtforms
Requires-Dist: dnspython
